benchling_mcp/__init__.py
benchling_mcp/server.py
benchling_mcp-0.1.1.dist-info/METADATA
benchling_mcp-0.1.1.dist-info/WHEEL
benchling_mcp-0.1.1.dist-info/entry_points.txt
benchling_mcp-0.1.1.dist-info/licenses/LICENSE
benchling_mcp-0.1.1.dist-info/RECORD
