Metadata-Version: 2.4
Name: benchling-mcp
Version: 0.1.1
Summary: MCP server for Benchling platform integration
Author-email: antonkulaga <antonkulaga@gmail.com>
License-File: LICENSE
Requires-Python: >=3.10
Requires-Dist: benchling-sdk>=1.22.0
Requires-Dist: biopython>=1.83
Requires-Dist: eliot>=1.17.5
Requires-Dist: fastapi>=0.115.13
Requires-Dist: fastmcp>=2.8.1
Requires-Dist: httpx>=0.25.0
Requires-Dist: pycomfort>=0.0.18
Requires-Dist: pydantic>=2.0.0
Requires-Dist: python-dotenv>=1.0.0
Requires-Dist: typer>=0.9.0
